smartload/__init__.py
smartload/smartload.py
smartload-1.0.1.dist-info/LICENSE
smartload-1.0.1.dist-info/METADATA
smartload-1.0.1.dist-info/WHEEL
smartload-1.0.1.dist-info/top_level.txt
smartload-1.0.1.dist-info/RECORD
