Metadata-Version: 2.1
Name: smartload
Version: 1.0.1
Summary: Smart loading of mat files
Home-page: https://github.com/nhat-le/smartload
Author: Nhat Le
Author-email: nmle@mit.edu
License: UNKNOWN
Download-URL: https://github.com/nhat-le/smartload/archive/refs/tags/v_05.tar.gz
Project-URL: Bug Tracker, https://github.com/pypa/sampleproject/issues
Platform: UNKNOWN
Classifier: Programming Language :: Python :: 3
Classifier: License :: OSI Approved :: MIT License
Classifier: Operating System :: OS Independent
Requires-Python: >=3.6
License-File: LICENSE
